RiceXL/RiceAlignment.py
RiceXL/RiceBorder.py
RiceXL/RiceExcel.py
RiceXL/RiceFont.py
RiceXL/RicePattern.py
RiceXL/RiceUtils.py
RiceXL/__init__.py
RiceXL/xlutils_newcopy.py
RiceXL-0.6.4.dist-info/LICENSE
RiceXL-0.6.4.dist-info/METADATA
RiceXL-0.6.4.dist-info/WHEEL
RiceXL-0.6.4.dist-info/top_level.txt
RiceXL-0.6.4.dist-info/RECORD
